ddgs/__init__.py
ddgs/base.py
ddgs/cli.py
ddgs/ddgs.py
ddgs/exceptions.py
ddgs/http_client.py
ddgs/http_client2.py
ddgs/py.typed
ddgs/results.py
ddgs/similarity.py
ddgs/utils.py
ddgs/engines/__init__.py
ddgs/engines/annasarchive.py
ddgs/engines/bing.py
ddgs/engines/bing_news.py
ddgs/engines/brave.py
ddgs/engines/duckduckgo.py
ddgs/engines/duckduckgo_images.py
ddgs/engines/duckduckgo_news.py
ddgs/engines/duckduckgo_videos.py
ddgs/engines/google.py
ddgs/engines/mojeek.py
ddgs/engines/wikipedia.py
ddgs/engines/yahoo.py
ddgs/engines/yahoo_news.py
ddgs/engines/yandex.py
ddgs-9.9.0.dist-info/licenses/LICENSE.md
ddgs-9.9.0.dist-info/METADATA
ddgs-9.9.0.dist-info/WHEEL
ddgs-9.9.0.dist-info/entry_points.txt
ddgs-9.9.0.dist-info/top_level.txt
ddgs-9.9.0.dist-info/RECORD
