Metadata-Version: 2.4
Name: ddgs
Version: 9.9.0
Summary: Dux Distributed Global Search. A metasearch library that aggregates results from diverse web search services.
Author: deedy5
License-Expression: MIT
Project-URL: Homepage, https://github.com/deedy5/ddgs
Keywords: python,search,metasearch
Classifier: Development Status :: 5 - Production/Stable
Classifier: Operating System :: OS Independent
Classifier: Programming Language :: Python :: 3
Classifier: Programming Language :: Python :: 3 :: Only
Classifier: Programming Language :: Python :: 3.10
Classifier: Programming Language :: Python :: 3.11
Classifier: Programming Language :: Python :: 3.12
Classifier: Programming Language :: Python :: 3.13
Classifier: Programming Language :: Python :: 3.14
Classifier: Programming Language :: Python :: Implementation :: CPython
Classifier: Topic :: Internet :: WWW/HTTP :: Indexing/Search
Classifier: Topic :: Software Development :: Libraries :: Python Modules
Requires-Python: >=3.10
License-File: LICENSE.md
Requires-Dist: click>=8.1.8
Requires-Dist: primp>=0.15.0
Requires-Dist: lxml>=4.9.4
Requires-Dist: httpx[brotli,http2,socks]>=0.28.1
Provides-Extra: dev
Requires-Dist: mypy>=1.17.1; extra == "dev"
Requires-Dist: pytest>=8.4.1; extra == "dev"
Requires-Dist: pytest-dependency>=0.6.0; extra == "dev"
Requires-Dist: ruff>=0.13.0; extra == "dev"
Dynamic: license-file
